Adafruit_LSM303-1.0.1.dist-info/metadata.json
Adafruit_LSM303-1.0.1.dist-info/METADATA
Adafruit_LSM303-1.0.1.dist-info/RECORD
Adafruit_LSM303-1.0.1.dist-info/WHEEL
Adafruit_LSM303-1.0.1.dist-info/DESCRIPTION.rst
Adafruit_LSM303-1.0.1.dist-info/dependency_links.txt
Adafruit_LSM303-1.0.1.dist-info/top_level.txt
Adafruit_LSM303/LSM303.py
Adafruit_LSM303/__init__.py
